Kanon4txt/__init__.py
Kanon4txt/k_anonym_try.py
Kanon4txt-0.0.1.dist-info/LICENSE
Kanon4txt-0.0.1.dist-info/METADATA
Kanon4txt-0.0.1.dist-info/WHEEL
Kanon4txt-0.0.1.dist-info/top_level.txt
Kanon4txt-0.0.1.dist-info/RECORD
